trixelserviceclient/__init__.py
trixelserviceclient/exception.py
trixelserviceclient/logging_helper.py
trixelserviceclient/schema.py
trixelserviceclient/extended_clients/pickle_client.py
trixelserviceclient/extended_clients/polling_client.py
trixelserviceclient-0.0.1.dist-info/LICENCE
trixelserviceclient-0.0.1.dist-info/METADATA
trixelserviceclient-0.0.1.dist-info/WHEEL
trixelserviceclient-0.0.1.dist-info/top_level.txt
trixelserviceclient-0.0.1.dist-info/RECORD
