Metadata-Version: 2.1
Name: trixelserviceclient
Version: 0.0.1
Summary: Simple Python client for participating in privacy aware environmental monitoring.
Author-email: Till <till@fleisch.dev>
Project-URL: Homepage, https://github.com/TillFleisch/TrixelServiceClient
Project-URL: Repository, https://github.com/TillFleisch/TrixelServiceClient.git
Project-URL: Issues, https://github.com/TillFleisch/TrixelServiceClient/issues
Keywords: trixel,private,privacy focused,environmental monitoring,sensor network
License-File: LICENCE
Requires-Dist: packaging
Requires-Dist: pynyhtm
Requires-Dist: trixellookupclient
Requires-Dist: trixelmanagementclient
Requires-Dist: colorlog
Requires-Dist: tomli ; python_version < "3.11"
Provides-Extra: dev
Requires-Dist: black ; extra == 'dev'
Requires-Dist: isort ; extra == 'dev'
